Workbook
Name NativeTimeline_Order_Date: #N/A
Name Slicer_Category: #N/A

Sheet Sales_Data
A1: Order_ID | B1: Order_Date | C1: Customer_Name | D1: Email | E1: City | F1: Region | G1: Product_ID | H1: Quantity | I1: Sales_Rep | J1: Status | K1: Discount | L1: Payment_Mode
A2: 1001 | B2: 12-01-2024 | C2: neha bajaj | D2: neha@abc.com | E2: Mumbai | F2: west | G2: P101 | H2: 3 | I2: Rahul mehta | J2: delivered | K2: 5% | L2: Online
A3: 1002 | B3: 15-01-2024 | C3: ARJUN VERMA | D3: arjun@xyz.com | E3: Delhi | F3: north | G3: P102 | H3: 2 | I3: priya shah | J3: Returned | L3: Cash
A4: 1003 | B4: 16-01-2024 | C4: Sneha rao | D4: sneha@abc.com | E4: pune | F4: west | G4: P105 | I4: Rahul Mehta | J4: Delivered | K4: n/a | L4: Online
A5: 1004 | B5: 18-01-2024 | C5: Ramesh Gupta | D5: ramesh@abc.com | E5: Chennai | F5: south | G5: P103 | H5: 1 | I5: Aman Jain | J5: delivered | K5: 0% | L5: Card
A6: 1005 | B6: 20-01-2024 | C6: Simran Kaur | D6: simran@xyz.com | E6: Delhi | F6: North | G6: P101 | H6: 2 | I6: Priya Shah | J6: Delivered | K6: 10% | L6: Cash
A7: 1006 | B7: 21-01-2024 | C7: Rahul Jain | D7: rahul@abc.com | E7: Bangalore | F7: South | G7: P104 | H7: 5 | I7: Deepak Sharma | J7: pending | L7: Online
A8: 1007 | B8: 25-01-2024 | C8: Anjali Singh | D8: anjali@xyz.com | E8: Pune | F8: WEST | G8: P102 | H8: 3 | I8: Rahul Mehta | J8: Delivered | L8: Online
A9: 1008 | B9: 26-01-2024 | C9: Karan Patel | D9: karan@abc.com | E9: Mumbai | F9: west | G9: P103 | H9: 4 | I9: Aman Jain | J9: Delivered | K9: 7% | L9: Cash
A10: 1009 | B10: 29-01-2024 | C10: Manish Joshi | D10: manish@abc.com | E10: Bangalore | F10: South | G10: P105 | H10: 2 | I10: Deepak Sharma | J10: Returned | L10: Card
A11: 1010 | B11: 31-01-2024 | C11: Kavita Bansal | D11: kavita@abc.com | E11: Chennai | F11: South | G11: P101 | I11: Aman Jain | J11: Delivered | K11: n/a | L11: Online

Sheet Sale 
A1: Order_ID | B1: Order_Date | C1: Month | D1: Year | E1: Customer_Name | F1: Email | G1: Region | H1: City | I1: order by city | J1: Product_ID | K1: Quantity | L1: Sales_Representative | M1: Category | N1: Status | O1: Discount | P1: Payment_Mode | Q1: High-Value Orders | R1: Final Amount | S1: Unit Price | T1: Average amount by category | U1: Total Revenu by city | V1: Total Amount | W1: order label
A2: 1001 | B2: 45303 | C2: =TEXT(Table1_3[[#This Row],[Order_Date]],"mmm") -> Jan | D2: =TEXT(Table1_3[[#This Row],[Order_Date]],"yyyy") -> 2024 | E2: Neha Bajaj | F2: neha@abc.com | G2: West | H2: Mumbai | I2: =COUNTIF(H2:H11,H2) -> 2 | J2: P101 | K2: 3 | L2: Rahul Mehta | M2: =VLOOKUP(J2:$J$11,Category_discount!$A$1:$C$5,2,0) -> Electronics | N2: Delivered | O2: =VLOOKUP(Table1_3[Product_ID],Category_discount!A1:C5,3,0) -> 0.1 | P2: Online | Q2: =IF(Table1_3[[#This Row],[Total Amount]]>10000,"High Value","Normal") -> Normal | R2: =Table1_3[[#This Row],[Unit Price]]-Table1_3[[#This Row],[Discount]] -> 2499.9 | S2: =VLOOKUP($J$2:$J$11,Product_Master!$A$1:$D$6,4,0) -> 2500 | T2: =AVERAGEIF(Table1_3[Category],Table1_3[[#This Row],[Category]],Table1_3[Total Amount]) -> 5833.3333 | U2: =SUMIF($H$2:$H$11,Table1_3[[#This Row],[City]],Table1_3[Total Amount]) -> 19500 | V2: =(Table1_3[[#This Row],[Quantity]]*Table1_3[[#This Row],[Unit Price]]) -> 7500 | W2: =CONCATENATE(Table1_3[[#This Row],[Order_ID]],"-",Table1_3[[#This Row],[Customer_Name]],"-",Table1_3[[#This Row],[Product_ID]]) -> 1001-Neha Bajaj-P101
A3: 1002 | B3: 45306 | C3: =TEXT(Table1_3[[#This Row],[Order_Date]],"mmm") -> Jan | D3: =TEXT(Table1_3[[#This Row],[Order_Date]],"yyyy") -> 2024 | E3: Arjun Verma | F3: arjun@xyz.com | G3: North | H3: Delhi | I3: =COUNTIF(H3:H12,H3) -> 3 | J3: P102 | K3: 2 | L3: Priya Shah | M3: =VLOOKUP(J3:$J$11,Category_discount!$A$1:$C$5,2,0) -> Furniture | N3: Returned | O3: =VLOOKUP(Table1_3[Product_ID],Category_discount!A2:C6,3,0) -> 0.08 | P3: Cash | Q3: =IF(Table1_3[[#This Row],[Total Amount]]>10000,"High Value","Normal") -> High Value | R3: =Table1_3[[#This Row],[Unit Price]]-Table1_3[[#This Row],[Discount]] -> 5999.92 | S3: =VLOOKUP($J$2:$J$11,Product_Master!$A$1:$D$6,4,0) -> 6000 | T3: =AVERAGEIF(Table1_3[Category],Table1_3[[#This Row],[Category]],Table1_3[Total Amount]) -> 23333.333 | U3: =SUMIF($H$2:$H$11,Table1_3[[#This Row],[City]],Table1_3[Total Amount]) -> 20000 | V3: =(Table1_3[[#This Row],[Quantity]]*Table1_3[[#This Row],[Unit Price]]) -> 12000 | W3: =CONCATENATE(Table1_3[[#This Row],[Order_ID]],"-",Table1_3[[#This Row],[Customer_Name]],"-",Table1_3[[#This Row],[Product_ID]]) -> 1002-Arjun Verma-P102
A4: 1003 | B4: 45307 | C4: =TEXT(Table1_3[[#This Row],[Order_Date]],"mmm") -> Jan | D4: =TEXT(Table1_3[[#This Row],[Order_Date]],"yyyy") -> 2024 | E4: Sneha Rao | F4: sneha@abc.com | G4: West | H4: Pune | I4: =COUNTIF(H4:H13,H4) -> 2 | J4: P105 | K4: 2 | L4: Rahul Mehta | M4: =VLOOKUP(J4:$J$11,Category_discount!$A$1:$C$5,2,0) -> Accessories | N4: Delivered | O4: =VLOOKUP(Table1_3[Product_ID],Category_discount!A3:C7,3,0) -> 0.07 | P4: Online | Q4: =IF(Table1_3[[#This Row],[Total Amount]]>10000,"High Value","Normal") -> Normal | R4: =Table1_3[[#This Row],[Unit Price]]-Table1_3[[#This Row],[Discount]] -> 1499.93 | S4: =VLOOKUP($J$2:$J$11,Product_Master!$A$1:$D$6,4,0) -> 1500 | T4: =AVERAGEIF(Table1_3[Category],Table1_3[[#This Row],[Category]],Table1_3[Total Amount]) -> 3000 | U4: =SUMIF($H$2:$H$11,Table1_3[[#This Row],[City]],Table1_3[Total Amount]) -> 21000 | V4: =(Table1_3[[#This Row],[Quantity]]*Table1_3[[#This Row],[Unit Price]]) -> 3000 | W4: =CONCATENATE(Table1_3[[#This Row],[Order_ID]],"-",Table1_3[[#This Row],[Customer_Name]],"-",Table1_3[[#This Row],[Product_ID]]) -> 1003-Sneha Rao-P105
A5: 1004 | B5: 45309 | C5: =TEXT(Table1_3[[#This Row],[Order_Date]],"mmm") -> Jan | D5: =TEXT(Table1_3[[#This Row],[Order_Date]],"yyyy") -> 2024 | E5: Ramesh Gupta | F5: ramesh@abc.com | G5: South | H5: delhi | I5: =COUNTIF(H5:H14,H5) -> 2 | J5: P103 | K5: 1 | L5: Aman Jain | M5: =VLOOKUP(J5:$J$11,Category_discount!$A$1:$C$5,2,0) -> Kitchen | N5: Delivered | O5: =VLOOKUP(Table1_3[Product_ID],Category_discount!A4:C8,3,0) -> 0.05 | P5: Card | Q5: =IF(Table1_3[[#This Row],[Total Amount]]>10000,"High Value","Normal") -> Normal | R5: =Table1_3[[#This Row],[Unit Price]]-Table1_3[[#This Row],[Discount]] -> 2999.95 | S5: =VLOOKUP($J$2:$J$11,Product_Master!$A$1:$D$6,4,0) -> 3000 | T5: =AVERAGEIF(Table1_3[Category],Table1_3[[#This Row],[Category]],Table1_3[Total Amount]) -> 7500 | U5: =SUMIF($H$2:$H$11,Table1_3[[#This Row],[City]],Table1_3[Total Amount]) -> 20000 | V5: =(Table1_3[[#This Row],[Quantity]]*Table1_3[[#This Row],[Unit Price]]) -> 3000 | W5: =CONCATENATE(Table1_3[[#This Row],[Order_ID]],"-",Table1_3[[#This Row],[Customer_Name]],"-",Table1_3[[#This Row],[Product_ID]]) -> 1004-Ramesh Gupta-P103
A6: 1005 | B6: 45311 | C6: =TEXT(Table1_3[[#This Row],[Order_Date]],"mmm") -> Jan | D6: =TEXT(Table1_3[[#This Row],[Order_Date]],"yyyy") -> 2024 | E6: Simran Kaur | F6: simran@xyz.com | G6: North | H6: Delhi | I6: =COUNTIF(H6:H15,H6) -> 1 | J6: P101 | K6: 2 | L6: Priya Shah | M6: =VLOOKUP(J6:$J$11,Category_discount!$A$1:$C$5,2,0) -> Electronics | N6: Delivered | O6: =VLOOKUP(J6:J11,Category_discount!A1:C5,3,0) -> 0.1 | P6: Cash | Q6: =IF(Table1_3[[#This Row],[Total Amount]]>10000,"High Value","Normal") -> Normal | R6: =Table1_3[[#This Row],[Unit Price]]-Table1_3[[#This Row],[Discount]] -> 2499.9 | S6: =VLOOKUP($J$2:$J$11,Product_Master!$A$1:$D$6,4,0) -> 2500 | T6: =AVERAGEIF(Table1_3[Category],Table1_3[[#This Row],[Category]],Table1_3[Total Amount]) -> 5833.3333 | U6: =SUMIF($H$2:$H$11,Table1_3[[#This Row],[City]],Table1_3[Total Amount]) -> 20000 | V6: =(Table1_3[[#This Row],[Quantity]]*Table1_3[[#This Row],[Unit Price]]) -> 5000 | W6: =CONCATENATE(Table1_3[[#This Row],[Order_ID]],"-",Table1_3[[#This Row],[Customer_Name]],"-",Table1_3[[#This Row],[Product_ID]]) -> 1005-Simran Kaur-P101
A7: 1006 | B7: 45312 | C7: =TEXT(Table1_3[[#This Row],[Order_Date]],"mmm") -> Jan | D7: =TEXT(Table1_3[[#This Row],[Order_Date]],"yyyy") -> 2024 | E7: Rahul Jain | F7: rahul@abc.com | G7: South | H7: Bangalore | I7: =COUNTIF(H7:H16,H7) -> 2 | J7: P104 | K7: 5 | L7: Deepak Sharma | M7: Furniture | N7: Pending | O7: 0 | P7: Online | Q7: =IF(Table1_3[[#This Row],[Total Amount]]>10000,"High Value","Normal") -> High Value | R7: =Table1_3[[#This Row],[Unit Price]]-Table1_3[[#This Row],[Discount]] -> 8000 | S7: =VLOOKUP($J$2:$J$11,Product_Master!$A$1:$D$6,4,0) -> 8000 | T7: =AVERAGEIF(Table1_3[Category],Table1_3[[#This Row],[Category]],Table1_3[Total Amount]) -> 23333.333 | U7: =SUMIF($H$2:$H$11,Table1_3[[#This Row],[City]],Table1_3[Total Amount]) -> 43000 | V7: =(Table1_3[[#This Row],[Quantity]]*Table1_3[[#This Row],[Unit Price]]) -> 40000 | W7: =CONCATENATE(Table1_3[[#This Row],[Order_ID]],"-",Table1_3[[#This Row],[Customer_Name]],"-",Table1_3[[#This Row],[Product_ID]]) -> 1006-Rahul Jain-P104
A8: 1007 | B8: 45316 | C8: =TEXT(Table1_3[[#This Row],[Order_Date]],"mmm") -> Jan | D8: =TEXT(Table1_3[[#This Row],[Order_Date]],"yyyy") -> 2024 | E8: Anjali Singh | F8: anjali@xyz.com | G8: West | H8: Pune | I8: =COUNTIF(H8:H17,H8) -> 1 | J8: P102 | K8: 3 | L8: Rahul Mehta | M8: =VLOOKUP(J8:$J$11,Category_discount!$A$1:$C$5,2,0) -> Furniture | N8: Delivered | O8: =VLOOKUP($J$7:$J$11,Category_discount!A2:C6,3,0) -> 0.08 | P8: Online | Q8: =IF(Table1_3[[#This Row],[Total Amount]]>10000,"High Value","Normal") -> High Value | R8: =Table1_3[[#This Row],[Unit Price]]-Table1_3[[#This Row],[Discount]] -> 5999.92 | S8: =VLOOKUP($J$2:$J$11,Product_Master!$A$1:$D$6,4,0) -> 6000 | T8: =AVERAGEIF(Table1_3[Category],Table1_3[[#This Row],[Category]],Table1_3[Total Amount]) -> 23333.333 | U8: =SUMIF($H$2:$H$11,Table1_3[[#This Row],[City]],Table1_3[Total Amount]) -> 21000 | V8: =(Table1_3[[#This Row],[Quantity]]*Table1_3[[#This Row],[Unit Price]]) -> 18000 | W8: =CONCATENATE(Table1_3[[#This Row],[Order_ID]],"-",Table1_3[[#This Row],[Customer_Name]],"-",Table1_3[[#This Row],[Product_ID]]) -> 1007-Anjali Singh-P102
A9: 1008 | B9: 45317 | C9: =TEXT(Table1_3[[#This Row],[Order_Date]],"mmm") -> Jan | D9: =TEXT(Table1_3[[#This Row],[Order_Date]],"yyyy") -> 2024 | E9: Karan Patel | F9: karan@abc.com | G9: West | H9: Mumbai | I9: =COUNTIF(H9:H18,H9) -> 1 | J9: P103 | K9: 4 | L9: Aman Jain | M9: =VLOOKUP(J9:$J$11,Category_discount!$A$1:$C$5,2,0) -> Kitchen | N9: Delivered | O9: =VLOOKUP($J$7:$J$11,Category_discount!A3:C7,3,0) -> 0.05 | P9: Cash | Q9: =IF(Table1_3[[#This Row],[Total Amount]]>10000,"High Value","Normal") -> High Value | R9: =Table1_3[[#This Row],[Unit Price]]-Table1_3[[#This Row],[Discount]] -> 2999.95 | S9: =VLOOKUP($J$2:$J$11,Product_Master!$A$1:$D$6,4,0) -> 3000 | T9: =AVERAGEIF(Table1_3[Category],Table1_3[[#This Row],[Category]],Table1_3[Total Amount]) -> 7500 | U9: =SUMIF($H$2:$H$11,Table1_3[[#This Row],[City]],Table1_3[Total Amount]) -> 19500 | V9: =(Table1_3[[#This Row],[Quantity]]*Table1_3[[#This Row],[Unit Price]]) -> 12000 | W9: =CONCATENATE(Table1_3[[#This Row],[Order_ID]],"-",Table1_3[[#This Row],[Customer_Name]],"-",Table1_3[[#This Row],[Product_ID]]) -> 1008-Karan Patel-P103
A10: 1009 | B10: 45320 | C10: =TEXT(Table1_3[[#This Row],[Order_Date]],"mmm") -> Jan | D10: =TEXT(Table1_3[[#This Row],[Order_Date]],"yyyy") -> 2024 | E10: Manish Joshi | F10: manish@abc.com | G10: South | H10: Bangalore | I10: =COUNTIF(H10:H19,H10) -> 1 | J10: P105 | K10: 2 | L10: Deepak Sharma | M10: =VLOOKUP(J10:$J$11,Category_discount!$A$1:$C$5,2,0) -> Accessories | N10: Returned | O10: =VLOOKUP($J$7:$J$11,Category_discount!A4:C8,3,0) -> 0.07 | P10: Card | Q10: =IF(Table1_3[[#This Row],[Total Amount]]>10000,"High Value","Normal") -> Normal | R10: =Table1_3[[#This Row],[Unit Price]]-Table1_3[[#This Row],[Discount]] -> 1499.93 | S10: =VLOOKUP($J$2:$J$11,Product_Master!$A$1:$D$6,4,0) -> 1500 | T10: =AVERAGEIF(Table1_3[Category],Table1_3[[#This Row],[Category]],Table1_3[Total Amount]) -> 3000 | U10: =SUMIF($H$2:$H$11,Table1_3[[#This Row],[City]],Table1_3[Total Amount]) -> 43000 | V10: =(Table1_3[[#This Row],[Quantity]]*Table1_3[[#This Row],[Unit Price]]) -> 3000 | W10: =CONCATENATE(Table1_3[[#This Row],[Order_ID]],"-",Table1_3[[#This Row],[Customer_Name]],"-",Table1_3[[#This Row],[Product_ID]]) -> 1009-Manish Joshi-P105
A11: 1010 | B11: 45322 | C11: =TEXT(Table1_3[[#This Row],[Order_Date]],"mmm") -> Jan | D11: =TEXT(Table1_3[[#This Row],[Order_Date]],"yyyy") -> 2024 | E11: Kavita Bansal | F11: kavita@abc.com | G11: South | H11: Chennai | I11: =COUNTIF(H11:H20,H11) -> 1 | J11: P101 | K11: 2 | L11: Aman Jain | M11: =VLOOKUP(J11:$J$11,Category_discount!$A$1:$C$5,2,0) -> Electronics | N11: Delivered | O11: =VLOOKUP(Table1_3[Product_ID],Category_discount!A1:C5,3,0) -> 0.1 | P11: Online | Q11: =IF(Table1_3[[#This Row],[Total Amount]]>10000,"High Value","Normal") -> Normal | R11: =Table1_3[[#This Row],[Unit Price]]-Table1_3[[#This Row],[Discount]] -> 2499.9 | S11: =VLOOKUP($J$2:$J$11,Product_Master!$A$1:$D$6,4,0) -> 2500 | T11: =AVERAGEIF(Table1_3[Category],Table1_3[[#This Row],[Category]],Table1_3[Total Amount]) -> 5833.3333 | U11: =SUMIF($H$2:$H$11,Table1_3[[#This Row],[City]],Table1_3[Total Amount]) -> 5000 | V11: =(Table1_3[[#This Row],[Quantity]]*Table1_3[[#This Row],[Unit Price]]) -> 5000 | W11: =CONCATENATE(Table1_3[[#This Row],[Order_ID]],"-",Table1_3[[#This Row],[Customer_Name]],"-",Table1_3[[#This Row],[Product_ID]]) -> 1010-Kavita Bansal-P101
R12: =SUM(R2:R11) -> 36499.3 | S12: =SUM(S2:S11) -> 36500 | T12: =SUM(T2:T11) -> 108500 | U12: =SUM(U2:U11) -> 232000 | V12: =SUBTOTAL(109,Table1_3[Total Amount]) -> 108500
V14: =SUM(Table1_3[Total Amount]) -> 108500

Sheet Sheet1
A1: Payment_Mode | B1: High-Value Orders | C1: Average amount by category | D1: Final Amount
A2: Online | B2: =IF(Table1_3[[#This Row],[Total Amount]]>10000,"High Value","Normal") -> Normal | C2: =AVERAGEIF(Table1_3[Category],Table1_3[[#This Row],[Category]],Table1_3[Total Amount]) -> 5833.3333 | D2: =Table1_3[[#This Row],[Unit Price]]-Table1_3[[#This Row],[Discount]] -> 2499.9 | F2: google
A3: Cash | B3: =IF(Table1_3[[#This Row],[Total Amount]]>10000,"High Value","Normal") -> High Value | C3: =AVERAGEIF(Table1_3[Category],Table1_3[[#This Row],[Category]],Table1_3[Total Amount]) -> 23333.333 | D3: =Table1_3[[#This Row],[Unit Price]]-Table1_3[[#This Row],[Discount]] -> 5999.92
A4: Online | B4: =IF(Table1_3[[#This Row],[Total Amount]]>10000,"High Value","Normal") -> Normal | C4: =AVERAGEIF(Table1_3[Category],Table1_3[[#This Row],[Category]],Table1_3[Total Amount]) -> 3000 | D4: =Table1_3[[#This Row],[Unit Price]]-Table1_3[[#This Row],[Discount]] -> 1499.93
A5: Card | B5: =IF(Table1_3[[#This Row],[Total Amount]]>10000,"High Value","Normal") -> Normal | C5: =AVERAGEIF(Table1_3[Category],Table1_3[[#This Row],[Category]],Table1_3[Total Amount]) -> 7500 | D5: =Table1_3[[#This Row],[Unit Price]]-Table1_3[[#This Row],[Discount]] -> 2999.95
A6: Cash | B6: =IF(Table1_3[[#This Row],[Total Amount]]>10000,"High Value","Normal") -> Normal | C6: =AVERAGEIF(Table1_3[Category],Table1_3[[#This Row],[Category]],Table1_3[Total Amount]) -> 5833.3333 | D6: =Table1_3[[#This Row],[Unit Price]]-Table1_3[[#This Row],[Discount]] -> 2499.9
A7: Online | B7: =IF(Table1_3[[#This Row],[Total Amount]]>10000,"High Value","Normal") -> High Value | C7: =AVERAGEIF(Table1_3[Category],Table1_3[[#This Row],[Category]],Table1_3[Total Amount]) -> 23333.333 | D7: =Table1_3[[#This Row],[Unit Price]]-Table1_3[[#This Row],[Discount]] -> 8000
A8: Online | B8: =IF(Table1_3[[#This Row],[Total Amount]]>10000,"High Value","Normal") -> High Value | C8: =AVERAGEIF(Table1_3[Category],Table1_3[[#This Row],[Category]],Table1_3[Total Amount]) -> 23333.333 | D8: =Table1_3[[#This Row],[Unit Price]]-Table1_3[[#This Row],[Discount]] -> 5999.92
A9: Cash | B9: =IF(Table1_3[[#This Row],[Total Amount]]>10000,"High Value","Normal") -> High Value | C9: =AVERAGEIF(Table1_3[Category],Table1_3[[#This Row],[Category]],Table1_3[Total Amount]) -> 7500 | D9: =Table1_3[[#This Row],[Unit Price]]-Table1_3[[#This Row],[Discount]] -> 2999.95
A10: Card | B10: =IF(Table1_3[[#This Row],[Total Amount]]>10000,"High Value","Normal") -> Normal | C10: =AVERAGEIF(Table1_3[Category],Table1_3[[#This Row],[Category]],Table1_3[Total Amount]) -> 3000 | D10: =Table1_3[[#This Row],[Unit Price]]-Table1_3[[#This Row],[Discount]] -> 1499.93
A11: Online | B11: =IF(Table1_3[[#This Row],[Total Amount]]>10000,"High Value","Normal") -> Normal | C11: =AVERAGEIF(Table1_3[Category],Table1_3[[#This Row],[Category]],Table1_3[Total Amount]) -> 5833.3333 | D11: =Table1_3[[#This Row],[Unit Price]]-Table1_3[[#This Row],[Discount]] -> 2499.9
F17: ←

Sheet Product_Master
A1: Product_ID | B1: Product_Name | C1: Category | D1: Unit_Price
A2: P101 | B2: Bluetooth Speaker | C2: Electronics | D2: 2500
A3: P102 | B3: Office Chair | C3: Furniture | D3: 6000
A4: P103 | B4: Coffee Maker | C4: Kitchen | D4: 3000
A5: P104 | B5: Study Table | C5: Furniture | D5: 8000
A6: P105 | B6: Laptop Stand | C6: Accessories | D6: 1500

Sheet Category_discount
A1: Product_id | B1: Category | C1: Standard_Discount
A2: =INDEX(Product_Master!A2:A6,MATCH(Category_discount!B2,Product_Master!C2:C6,0)) -> P101 | B2: Electronics | C2: 0.1
A3: =INDEX(Product_Master!A3:A7,MATCH(Category_discount!B3,Product_Master!C3:C7,0)) -> P102 | B3: Furniture | C3: 0.08
A4: =INDEX(Product_Master!A4:A8,MATCH(Category_discount!B4,Product_Master!C4:C8,0)) -> P103 | B4: Kitchen | C4: 0.05
A5: =INDEX(Product_Master!A5:A9,MATCH(Category_discount!B5,Product_Master!C5:C9,0)) -> P105 | B5: Accessories | C5: 0.07

Sheet orders and sale by city
A3: Row Labels | B3: Sum of Order_ID | C3: Sum of Total Amount
A4: Chennai | B4: 1010 | C4: 5000
A5: Mumbai | B5: 2009 | C5: 19500
A6: Delhi | B6: 3011 | C6: 20000
A7: Pune | B7: 2010 | C7: 21000
A8: Bangalore | B8: 2015 | C8: 43000
A9: Grand Total | B9: 10055 | C9: 108500

Sheet Sale by Category
A3: Row Labels | B3: Total Amounts
A4: Accessories | B4: 6000
A5: Jan | B5: 6000
A6: 2024 | B6: 6000
A7: Electronics | B7: 17500
A8: Jan | B8: 17500
A9: 2024 | B9: 17500
A10: Furniture | B10: 70000
A11: Jan | B11: 70000
A12: 2024 | B12: 70000
A13: Kitchen | B13: 15000
A14: Jan | B14: 15000
A15: 2024 | B15: 15000
A16: Grand Total | B16: 108500

Sheet orders by region
A1: Row Labels | B1: Sum of Order_ID
A2: North | B2: 2007
A3: South | B3: 4029
A4: West | B4: 4019
A5: Grand Total | B5: 10055

Sheet step
A1: Column1
A2: 1. Remove extra spaces from Customer_Name.
A3: 2. Convert all names in Customer_Name to proper case.
A4: 3. Fill missing discounts using VLOOKUP from Category_Discounts sheet.
A5: 4. Convert Order_Date into dd-mm-yyyy format.
A6: 5. Calculate Total Amount (Before Discount) = Quantity * Unit_Price.
A7: 6. Calculate Final Amount (After Discount) = Total_Amount * (1 - Discount).
A8: 7. Add a Month column using TEXT(Order_Date,"mmm").
A9: 8. Add a Year column using YEAR(Order_Date).
A10: 9. Identify High-Value Orders (IF Final_Amount > 10000 then "High Value" else "Normal").
A11: 10. Replace missing City values with "Not Specified" using IF().
A12: 11. Create a Full Order Label = CONCATENATE(Order_ID, " - ", Customer_Name, " - ", Product).
... A24: - Monthly Sales Trend (Chart)
